commented_configparser-3.0.0.dist-info/licenses/LICENSE
commentedconfigparser/__init__.py
commentedconfigparser/commentedconfigparser.py
commentedconfigparser/py.typed
commented_configparser-3.0.0.dist-info/METADATA
commented_configparser-3.0.0.dist-info/WHEEL
commented_configparser-3.0.0.dist-info/top_level.txt
commented_configparser-3.0.0.dist-info/RECORD
