Metadata-Version: 2.4
Name: commented-configparser
Version: 3.0.0
Summary: A custom ConfigParser class that preserves comments and most formatting when writing loaded config out.
Author-email: Preocts <preocts@preocts.com>
License-Expression: MIT
Project-URL: homepage, https://github.com/Preocts/commented-configparser
Classifier: Programming Language :: Python :: 3
Classifier: Programming Language :: Python :: 3 :: Only
Classifier: Programming Language :: Python :: Implementation :: CPython
Requires-Python: >=3.9
License-File: LICENSE
Provides-Extra: dev
Requires-Dist: flake8; extra == "dev"
Requires-Dist: flake8-builtins; extra == "dev"
Requires-Dist: flake8-pep585; extra == "dev"
Requires-Dist: black; extra == "dev"
Requires-Dist: isort; extra == "dev"
Requires-Dist: mypy; extra == "dev"
Provides-Extra: test
Requires-Dist: pytest; extra == "test"
Requires-Dist: pytest-randomly; extra == "test"
Requires-Dist: coverage; extra == "test"
Dynamic: license-file
